aind_disrnn_utils/__init__.py
aind_disrnn_utils/data_loader.py
aind_disrnn_utils/data_models.py
aind_disrnn_utils-0.0.15.dist-info/licenses/LICENSE
aind_disrnn_utils-0.0.15.dist-info/METADATA
aind_disrnn_utils-0.0.15.dist-info/WHEEL
aind_disrnn_utils-0.0.15.dist-info/top_level.txt
aind_disrnn_utils-0.0.15.dist-info/RECORD
