Metadata-Version: 2.4
Name: aind_disrnn_utils
Version: 0.0.15
Summary: Generated from aind-library-template
Author: Allen Institute for Neural Dynamics
License: MIT
Classifier: Programming Language :: Python :: 3
Requires-Python: >=3.11
License-File: LICENSE
Requires-Dist: numpy
Requires-Dist: disentangled-rnns
Dynamic: license-file
